Workbook

Sheet README
A1: 💰 Bosch CCTV Dashboard — Cost Calculator
A3: วิธีใช้:
A4: 1. | B4: ไปที่ sheet 'Inputs' — แก้ตัวเลขในเซลล์สีเหลือง (input cells)
A5: 2. | B5: ไปที่ sheet 'Rate Card' — ปรับ man-hour rate ตามนโยบายบริษัท
A6: 3. | B6: Sheet 'Tier Calc' — แสดงต้นทุนแยกตาม tier (G1-G5) คำนวณอัตโนมัติ
A7: 4. | B7: Sheet 'MA Plans' — เปรียบเทียบ Bronze / Silver / Gold ทุก tier
A8: 5. | B8: Sheet 'Summary' — สรุป Year 1, Year 2-5, 5-year TCO และราคาเสนอลูกค้า
A9: 6. | B9: Sheet 'ROI' — เครื่องคำนวณ ROI สำหรับนำเสนอลูกค้า
A11: 📌 | B11: เซลล์สีเหลืองข้อความ้น้ำเงิน = Input (แก้ได้)
A12: 📌 | B12: เซลล์ข้อความสีดำ = สูตรคำนวณ (อย่าแก้)
A13: 📌 | B13: เซลล์ข้อความสีเขียว = Reference จาก sheet อื่น
A16: Color Coding (Industry Standard)
A18: 🟦 Input | B18: ตัวเลขที่ผู้ใช้แก้ได้ (สีน้ำเงิน, พื้นเหลือง)
A19: ⬛ Formula | B19: สูตรคำนวณ (สีดำ) — อย่าแก้
A20: 🟩 Link | B20: อ้างอิงข้าม sheet (สีเขียว)
A22: Document version 1.0 — May 2026

Sheet Rate Card
A1: 💼 Man-Hour Rate Card
A3: Role | B3: Rate (THB/hour) | C3: Rate (THB/day-8hr) | D3: Note
A4: Junior Developer | B4: 600 | C4: =B4*8 | D4: < 2 ปีประสบการณ์
A5: Mid-level Developer | B5: 1000 | C5: =B5*8 | D5: 2-5 ปี
A6: Senior Developer | B6: 1500 | C6: =B6*8 | D6: 5-10 ปี
A7: Tech Lead/Architect | B7: 2500 | C7: =B7*8 | D7: > 10 ปี + design experience
A8: Solution Architect | B8: 3000 | C8: =B8*8 | D8: Enterprise level
A9: DevOps Engineer | B9: 1800 | C9: =B9*8 | D9: Docker/K8s expertise
A10: DevOps Lead | B10: 2500 | C10: =B10*8 | D10: K8s + multi-cluster
A11: Database Admin | B11: 2000 | C11: =B11*8 | D11: PostgreSQL/scaling
A12: DBA Senior | B12: 2500 | C12: =B12*8 | D12: TimescaleDB/Citus
A13: System Engineer | B13: 1200 | C13: =B13*8 | D13: Network/server admin
A14: Security Engineer | B14: 2200 | C14: =B14*8 | D14: Pen test + hardening
A15: Network Engineer | B15: 1500 | C15: =B15*8 | D15: Datacenter networking
... A23: QA Lead | B23: 1500 | C23: =B23*8 | D23: Test strategy
A26: 📝 Note: Rate รวม overhead 30% (employer cost vs. salary). Outsource สูงกว่า 1.5-2x

Sheet Inputs
A1: 🎛 Project Inputs (แก้ได้ตามต้องการ)
A3: 1. Tier Camera Capacity
A4: Tier | B4: Cameras | C4: Hardware (THB) | D4: Hidden Cost (THB/yr) | E4: Hardware refresh % | F4: Note
A5: G1 | B5: 200 | C5: 80000 | D5: 63200 | E5: 0.2 | F5: Single server
A6: G2 | B6: 500 | C6: 240000 | D6: 179200 | E6: 0.2 | F6: Split app + DB
A7: G3 | B7: 1000 | C7: 1200000 | D7: 1080000 | E7: 0.2 | F7: Distributed + LB
A8: G4 | B8: 2000 | C8: 3500000 | D8: 4020000 | E8: 0.2 | F8: Kubernetes + HA
A9: G5 | B9: 3000 | C9: 12000000 | D9: 18600000 | E9: 0.2 | F9: Multi-zone + Edge
A12: 2. Implementation Hours by Activity (per tier)
A13: Activity | B13: G1 (200) | C13: G2 (500) | D13: G3 (1000) | E13: G4 (2000) | F13: G5 (3000)
A14: Pre-sales & Requirement | B14: 16 | C14: 24 | D14: 40 | E14: 80 | F14: 160
A15: Hardware Setup | B15: 24 | C15: 48 | D15: 120 | E15: 320 | F15: 800
A16: Software Deployment | B16: 16 | C16: 32 | D16: 80 | E16: 240 | F16: 600
A17: Camera Onboarding | B17: 16 | C17: 40 | D17: 80 | E17: 160 | F17: 240
A18: Customization | B18: 16 | C18: 24 | D18: 40 | E18: 80 | F18: 120
A19: Testing & UAT | B19: 24 | C19: 40 | D19: 80 | E19: 200 | F19: 400
A20: Training | B20: 8 | C20: 16 | D20: 32 | E20: 64 | F20: 120
A21: Documentation | B21: 8 | C21: 16 | D21: 24 | E21: 48 | F21: 80
A22: Project Management | B22: 24 | C22: 40 | D22: 80 | E22: 200 | F22: 400
A23: Travel + on-site | B23: 8 | C23: 16 | D23: 40 | E23: 80 | F23: 160
A24: TOTAL HOURS | B24: =SUM(B14:B23) | C24: =SUM(C14:C23) | D24: =SUM(D14:D23) | E24: =SUM(E14:E23) | F24: =SUM(F14:F23)
A26: 3. Average Blended Rate per Tier (THB/hour)
A27: Tier | B27: Blended Rate | C27: Note
A28: G1 | B28: 1385 | C28: More junior, single team
A29: G2 | B29: 1545 | C29: Mix senior + DBA
A30: G3 | B30: 1700 | C30: Architect + specialists
A31: G4 | B31: 1840 | C31: K8s expertise
A32: G5 | B32: 2140 | C32: Multi-architect, leads
A35: 4. Pricing Settings
A36: Gross Margin Target | B36: 0.33 | C36: ส่วนต่างกำไรที่ต้องการ
A37: Inflation Rate (Year 2-5) | B37: 0.03 | C37: ปรับ MA + Hidden cost รายปี
A38: Discount Multi-year MA | B38: 0.12 | C38: Discount ถ้าทำสัญญาหลายปี
A39: Discount Cloud TCO | B39: 0.85 | C39: Cloud cost = on-prem × this

Sheet Tier Calc
A1: 🧮 Implementation Cost Breakdown by Tier
A3: Tier | B3: Total Hours | C3: Blended Rate | D3: Implementation | E3: Hardware | F3: Hidden (Y1) | G3: TOTAL Year 1
A4: G1 | B4: =Inputs!B24 | C4: =Inputs!B28 | D4: =B4*C4 | E4: =Inputs!C5 | F4: =Inputs!D5 | G4: =D4+E4+F4
A5: G2 | B5: =Inputs!C24 | C5: =Inputs!B29 | D5: =B5*C5 | E5: =Inputs!C6 | F5: =Inputs!D6 | G5: =D5+E5+F5
A6: G3 | B6: =Inputs!D24 | C6: =Inputs!B30 | D6: =B6*C6 | E6: =Inputs!C7 | F6: =Inputs!D7 | G6: =D6+E6+F6
A7: G4 | B7: =Inputs!E24 | C7: =Inputs!B31 | D7: =B7*C7 | E7: =Inputs!C8 | F7: =Inputs!D8 | G7: =D7+E7+F7
A8: G5 | B8: =Inputs!F24 | C8: =Inputs!B32 | D8: =B8*C8 | E8: =Inputs!C9 | F8: =Inputs!D9 | G8: =D8+E8+F8
A10: 📝 Note: TOTAL Year 1 ยังไม่รวม MA — ดู MA Plans sheet
A13: 💰 Cost Component % per Tier
A14: Tier | B14: Hardware % | C14: Implementation % | D14: Hidden %
A15: G1 | B15: =E4/G4 | C15: =D4/G4 | D15: =F4/G4
A16: G2 | B16: =E5/G5 | C16: =D5/G5 | D16: =F5/G5
A17: G3 | B17: =E6/G6 | C17: =D6/G6 | D17: =F6/G6
A18: G4 | B18: =E7/G7 | C18: =D7/G7 | D18: =F7/G7
A19: G5 | B19: =E8/G8 | C19: =D8/G8 | D19: =F8/G8

Sheet MA Plans
A1: 🛠 Maintenance Agreement (MA) — Annual Cost
A3: Reserved Manpower Hours/Year (input)
A4: Tier | B4: Bronze | C4: Silver | D4: Gold
A5: G1 | B5: 80 | C5: 200 | D5: 480
A6: G2 | B6: 160 | C6: 400 | D6: 960
A7: G3 | B7: 320 | C7: 800 | D7: 2000
A8: G4 | B8: 800 | C8: 2000 | D8: 4000
A9: G5 | B9: 1600 | C9: 4000 | D9: 8000
A12: Annual MA Cost (THB)
A13: Tier | B13: Bronze (12-15%) | C13: Silver (18-22%) | D13: Gold (25-30%) | E13: Implementation (ref)
A14: G1 | B14: =B5*Inputs!B28*1+30000 | C14: =C5*Inputs!B28*1.05+50000 | D14: =D5*Inputs!B28*1.1+150000 | E14: ='Tier Calc'!D4
A15: G2 | B15: =B6*Inputs!B29*0.95+60000 | C15: =C6*Inputs!B29*1+100000 | D15: =D6*Inputs!B29*1.05+300000 | E15: ='Tier Calc'!D5
A16: G3 | B16: =B7*Inputs!B30*0.9+120000 | C16: =C7*Inputs!B30*0.95+200000 | D16: =D7*Inputs!B30*1+600000 | E16: ='Tier Calc'!D6
A17: G4 | B17: =B8*Inputs!B31*0.85+240000 | C17: =C8*Inputs!B31*0.9+400000 | D17: =D8*Inputs!B31*0.95+1200000 | E17: ='Tier Calc'!D7
A18: G5 | B18: =B9*Inputs!B32*0.8+480000 | C18: =C9*Inputs!B32*0.85+800000 | D18: =D9*Inputs!B32*0.9+2400000 | E18: ='Tier Calc'!D8
A21: MA as % of Implementation Cost
A22: Tier | B22: Bronze % | C22: Silver % | D22: Gold %
A23: G1 | B23: =B14/E14 | C23: =C14/E14 | D23: =D14/E14
A24: G2 | B24: =B15/E15 | C24: =C15/E15 | D24: =D15/E15
A25: G3 | B25: =B16/E16 | C25: =C16/E16 | D25: =D16/E16
A26: G4 | B26: =B17/E17 | C26: =C17/E17 | D26: =D17/E17
A27: G5 | B27: =B18/E18 | C27: =C18/E18 | D27: =D18/E18
A30: 📋 MA Plan Comparison
A31: Feature | B31: Bronze | C31: Silver | D31: Gold
A32: Coverage | B32: 8x5 Mon-Fri 9-17 | C32: 8x5 + Quarterly Review | D32: 24x7 + SLA
A33: P1 Response | B33: 8 hours | C33: 4 hours | D33: 1 hour
A34: P1 Resolution | B34: Best effort | C34: 8 hours | D34: 4 hours
A35: Bug fix critical | B35: ✓ | C35: ✓ | D35: ✓
A36: Bug fix non-critical | B36: — | C36: ✓ | D36: ✓
A37: Security patches | B37: Monthly | C37: Monthly | D37: Bi-weekly
A38: Feature requests | B38: — | C38: ≤8 hr/month | D38: ≤40 hr/month
A39: On-site visits | B39: — | C39: 4×/year | D39: Monthly
A40: Quarterly review | B40: — | C40: ✓ | D40: ✓
A41: DR drill | B41: — | C41: — | D41: 2×/year
A42: Uptime SLA | B42: Best effort | C42: 99% (business hours) | D42: 99.9%

Sheet Summary
A1: 📊 TCO Summary — 5-Year Projection
A3: 📌 Selected MA Plan: | B3: Silver | C3: (เลือกได้: Bronze / Silver / Gold)
A5: Tier | B5: Cameras | C5: Year 1 Total | D5: Year 2-5 (each) | E5: 5-Year TCO | F5: Per Camera/Year | G5: Suggested Sale Price | H5: Gross Margin
A6: G1 | B6: =Inputs!B5 | C6: ='Tier Calc'!G4+IF($B$3="Bronze",'MA Plans'!B14,IF($B$3="Silver",'MA Plans'!C14,'MA Plans'!D14)) | D6: =(IF($B$3="Bronze",'MA Plans'!B14,IF($B$3="Silver",'MA Plans'!C14,'MA Plans'!D14))+Inputs!D5+Inputs!C5*Inputs!E5)*(1+Inputs!B37) | E6: =C6+4*D6 | F6: =E6/B6/5 | G6: =E6/(1-Inputs!B36) | H6: =(G6-E6)/G6
A7: G2 | B7: =Inputs!B6 | C7: ='Tier Calc'!G5+IF($B$3="Bronze",'MA Plans'!B15,IF($B$3="Silver",'MA Plans'!C15,'MA Plans'!D15)) | D7: =(IF($B$3="Bronze",'MA Plans'!B15,IF($B$3="Silver",'MA Plans'!C15,'MA Plans'!D15))+Inputs!D6+Inputs!C6*Inputs!E6)*(1+Inputs!B37) | E7: =C7+4*D7 | F7: =E7/B7/5 | G7: =E7/(1-Inputs!B36) | H7: =(G7-E7)/G7
A8: G3 | B8: =Inputs!B7 | C8: ='Tier Calc'!G6+IF($B$3="Bronze",'MA Plans'!B16,IF($B$3="Silver",'MA Plans'!C16,'MA Plans'!D16)) | D8: =(IF($B$3="Bronze",'MA Plans'!B16,IF($B$3="Silver",'MA Plans'!C16,'MA Plans'!D16))+Inputs!D7+Inputs!C7*Inputs!E7)*(1+Inputs!B37) | E8: =C8+4*D8 | F8: =E8/B8/5 | G8: =E8/(1-Inputs!B36) | H8: =(G8-E8)/G8
A9: G4 | B9: =Inputs!B8 | C9: ='Tier Calc'!G7+IF($B$3="Bronze",'MA Plans'!B17,IF($B$3="Silver",'MA Plans'!C17,'MA Plans'!D17)) | D9: =(IF($B$3="Bronze",'MA Plans'!B17,IF($B$3="Silver",'MA Plans'!C17,'MA Plans'!D17))+Inputs!D8+Inputs!C8*Inputs!E8)*(1+Inputs!B37) | E9: =C9+4*D9 | F9: =E9/B9/5 | G9: =E9/(1-Inputs!B36) | H9: =(G9-E9)/G9
A10: G5 | B10: =Inputs!B9 | C10: ='Tier Calc'!G8+IF($B$3="Bronze",'MA Plans'!B18,IF($B$3="Silver",'MA Plans'!C18,'MA Plans'!D18)) | D10: =(IF($B$3="Bronze",'MA Plans'!B18,IF($B$3="Silver",'MA Plans'!C18,'MA Plans'!D18))+Inputs!D9+Inputs!C9*Inputs!E9)*(1+Inputs!B37) | E10: =C10+4*D10 | F10: =E10/B10/5 | G10: =E10/(1-Inputs!B36) | H10: =(G10-E10)/G10
A13: 📅 Year-by-Year Cost (with inflation)
A14: Tier | B14: Year 1 | C14: Year 2 | D14: Year 3 | E14: Year 4 | F14: Year 5 | G14: 5-Year Total | H14: Avg/Year
A15: G1 | B15: =C6 | C15: =D6 | D15: =C15*(1+Inputs!B37) | E15: =D15*(1+Inputs!B37) | F15: =E15*(1+Inputs!B37) | G15: =SUM(B15:F15) | H15: =G15/5
A16: G2 | B16: =C7 | C16: =D7 | D16: =C16*(1+Inputs!B37) | E16: =D16*(1+Inputs!B37) | F16: =E16*(1+Inputs!B37) | G16: =SUM(B16:F16) | H16: =G16/5
A17: G3 | B17: =C8 | C17: =D8 | D17: =C17*(1+Inputs!B37) | E17: =D17*(1+Inputs!B37) | F17: =E17*(1+Inputs!B37) | G17: =SUM(B17:F17) | H17: =G17/5
A18: G4 | B18: =C9 | C18: =D9 | D18: =C18*(1+Inputs!B37) | E18: =D18*(1+Inputs!B37) | F18: =E18*(1+Inputs!B37) | G18: =SUM(B18:F18) | H18: =G18/5
A19: G5 | B19: =C10 | C19: =D10 | D19: =C19*(1+Inputs!B37) | E19: =D19*(1+Inputs!B37) | F19: =E19*(1+Inputs!B37) | G19: =SUM(B19:F19) | H19: =G19/5

Sheet ROI
A1: 💵 ROI Calculator — Customer Justification
A3: Selected Tier: | B3: G3 | C3: (G1, G2, G3, G4, G5)
A4: Annual TCO (5y avg): | B4: =VLOOKUP(B3,Summary!A6:H10,5,FALSE)/5
A6: Annual Benefits (กรอกตัวเลขลูกค้า)
A7: Item | B7: Annual Value (THB) | C7: Note
A8: ป้องกัน theft / vandalism | B8: 1000000 | C8: 2 incidents/ปี × 500K (ตัวอย่าง)
A9: ลดจำนวน security guard | B9: 900000 | C9: ลด 3 คน × 25K/เดือน × 12
A10: Insurance premium ลด 15% | B10: 300000 | C10: อัตราที่ insurance ให้
A11: Productivity gain | B11: 600000 | C11: Faster incident response
A12: ลด liability claims | B12: 200000 | C12: บันทึกหลักฐาน video
A13: เพิ่มประสิทธิภาพ operation | B13: 400000 | C13: Real-time monitoring
A14: TOTAL ANNUAL BENEFIT | B14: =SUM(B8:B13)
A16: 📈 ROI Metrics
A17: Net Annual Benefit | B17: =B14-B4
A18: Annual ROI % | B18: =IFERROR((B14-B4)/B4,0)
A19: Payback Period (years) | B19: =IFERROR(VLOOKUP(B3,Summary!A6:H10,5,FALSE)/(B14-B4),99)
A20: 5-Year Net Value | B20: =B14*5-VLOOKUP(B3,Summary!A6:H10,5,FALSE)
